cnd_io/VERSION
cnd_io/__init__.py
cnd_io/__version__.py
cnd_io/cnd_io.py
cnd_io/cnd_provider.py
cnd_io/cnd_provider_gitlab.py
cnd_io/cnd_provider_localfile.py
CndIO-2.4.0.dist-info/METADATA
CndIO-2.4.0.dist-info/WHEEL
CndIO-2.4.0.dist-info/top_level.txt
CndIO-2.4.0.dist-info/RECORD
