Metadata-Version: 2.1
Name: CndIO
Version: 2.4.0
Summary: Tools to manage In/Out file. Easy to add new class if you need to change source/dest (file system, git ...)
Home-page: https://gitlab.com/changendevops/cnd-io
Author: Denis FABIEN
Author-email: denis.fabien@changendevops.com
License: MIT/X11
Project-URL: Documentation, https://changendevops.com
Project-URL: Source, https://gitlab.com/changendevops/cnd-io
Classifier: License :: OSI Approved :: MIT License
Classifier: Operating System :: OS Independent
Requires-Dist: clint
Requires-Dist: coverage
